<annotation verified="yes">
    <folder>Annotation</folder>
    <filename>u23.jpg</filename>
    <path>item-PascalVOC-export/Annotations/u23.jpg</path>
    <source>
        <database>Unknown</database>
    </source>
    <size>
        <width>1280</width>
        <height>720</height>
        <depth>3</depth>
    </size>
    <segmented>0</segmented>
    <object>
    <name>u</name>
    <pose>Unspecified</pose>
    <truncated>0</truncated>
    <difficult>0</difficult>
    <bndbox>
        <xmin>396.96760854583044</xmin>
        <ymin>62.7297794117647</ymin>
        <xmax>703.9558924879393</xmax>
        <ymax>650.3768382352941</ymax>
    </bndbox>
</object>
</annotation>
